docs/source/conf.py
nrrd/__init__.py
nrrd/_version.py
nrrd/errors.py
nrrd/formatters.py
nrrd/parsers.py
nrrd/reader.py
nrrd/types.py
nrrd/writer.py
pynrrd-1.1.2.dist-info/AUTHORS
pynrrd-1.1.2.dist-info/LICENSE
pynrrd-1.1.2.dist-info/METADATA
pynrrd-1.1.2.dist-info/WHEEL
pynrrd-1.1.2.dist-info/top_level.txt
pynrrd-1.1.2.dist-info/RECORD
