Metadata-Version: 2.2
Name: pynrrd
Version: 1.1.2
Summary: Pure python module for reading and writing NRRD files.
Author-email: Maarten Everts <me@nn8.nl>, Addison Elliott <addison.elliott@gmail.com>
License: Copyright (c) 2012 Maarten H. Everts and contributors. See AUTHORS for more
Project-URL: Homepage, https://github.com/mhe/pynrrd
Project-URL: Documentation, https://pynrrd.readthedocs.io/en/stable
Project-URL: Tracker, https://github.com/mhe/pynrrd/issues
Keywords: nrrd,teem,image,processing,file,format
Classifier: License :: OSI Approved :: MIT License
Classifier: Topic :: Scientific/Engineering
Classifier: Programming Language :: Python
Classifier: Programming Language :: Python :: 3.7
Classifier: Programming Language :: Python :: 3.8
Classifier: Programming Language :: Python :: 3.9
Classifier: Programming Language :: Python :: 3.10
Classifier: Programming Language :: Python :: 3.11
Classifier: Programming Language :: Python :: 3.12
Classifier: Programming Language :: Python :: 3.13
Requires-Python: >=3.7
License-File: LICENSE
License-File: AUTHORS
Requires-Dist: numpy>=1.21
Requires-Dist: typing_extensions
Provides-Extra: dev
Requires-Dist: build; extra == "dev"
Requires-Dist: pre-commit; extra == "dev"
Requires-Dist: pytest; extra == "dev"
